setup.py
keystone/__init__.py
keystone/action.py
keystone/api.py
keystone/api_allow_classes.py
keystone/broker.py
keystone/commission.py
keystone/constant.py
keystone/coordinator.py
keystone/drain.py
keystone/engine.cpython-35m-darwin.so
keystone/engine.so
keystone/exception.py
keystone/history.py
keystone/order.py
keystone/parameters.py
keystone/portfolio.py
keystone/py3compat.py
keystone/riskless.py
keystone/slippage.py
keystone/strategy.py
keystone/universe.py
keystone/app_client/__init__.py
keystone/app_client/client.py
keystone/app_client/datetime_breakpoint.py
keystone/app_client/kpdb.py
keystone/app_client/session.py
keystone/engine/__init__.py
keystone/engine/ksevent_engine.py
keystone/performance/__init__.py
keystone/performance/analyzer.py
keystone/performance/analyzer_deprecated.py
keystone/performance/perf.py
keystone/performance/risk.py
keystone/performance/sample_rate.py
keystone/sources/__init__.py
keystone/sources/app_source.py
keystone/sources/csv_source.py
keystone/sources/kstable.py
keystone/utils/__init__.py
keystone/utils/json_utils.py
keystone/utils/math_utils.py
keystone/utils/numpy_utils.py
keystone/utils/zmq_utils.py
keystone_sdk.egg-info/PKG-INFO
keystone_sdk.egg-info/SOURCES.txt
keystone_sdk.egg-info/dependency_links.txt
keystone_sdk.egg-info/requires.txt
keystone_sdk.egg-info/top_level.txt
test/test_strategy.py