Metadata-Version: 1.0
Name: keystone-sdk
Version: 0.7.13
Summary: keystone python SDK for backtesting
Home-page: UNKNOWN
Author: UNKNOWN
Author-email: UNKNOWN
License: UNKNOWN
Platform: UNKNOWN
